corefolio/__init__.py
corefolio/constraint.py
corefolio/optimizer.py
corefolio/universe.py
corefolio-0.2.2.dist-info/LICENSE
corefolio-0.2.2.dist-info/METADATA
corefolio-0.2.2.dist-info/WHEEL
corefolio-0.2.2.dist-info/top_level.txt
corefolio-0.2.2.dist-info/RECORD
