Metadata-Version: 2.2
Name: corefolio
Version: 0.2.2
Summary: A package for optimizing asset selection using CVXPY.
Author-email: Sebastien Eveno <sebastien.louis.eveno@gmail.com>
License: MIT License
Classifier: Programming Language :: Python :: 3.10
Classifier: Programming Language :: Python :: 3.11
Requires-Python: >=3.10
License-File: LICENSE
Requires-Dist: pandas==1.5.1
Requires-Dist: cvxpy==1.6.2
Requires-Dist: pytest==8.3.5
Requires-Dist: numpy==1.26.4
